[
  {
    "id": 1,
    "name": "LVB vs GBR",
    "imageSrc": "https://akthemes.com/video/images/matches/01.jpg"
  },
  {
    "id": 2,
    "name": "LVB vs GBR",
    "imageSrc": "https://akthemes.com/video/images/matches/02.jpg"


  },
  {
    "id": 3,
    "name": "LVB vs GBR",
    "imageSrc": "https://akthemes.com/video/images/matches/03.jpg"
  },
  {
    "id": 4,
    "name": "LVB vs GBR",
    "imageSrc": "https://akthemes.com/video/images/matches/04.jpg"
  },
  {
    "id": 5,
    "name": "LVB vs GBR",
    "imageSrc": "https://akthemes.com/video/images/matches/05.jpg"

  },
  {
    "id": 6,
    "name": "LVB vs GBR",
    "imageSrc": "https://akthemes.com/video/images/matches/06.jpg"
  },
  {
    "id": 7,
    "name": "LVB vs GBR",
    "imageSrc": "https://akthemes.com/video/images/matches/07.jpg"
  },
  {
    "id": 8,
    "name": "LVB vs GBR",
    "imageSrc": "https://akthemes.com/video/images/matches/07.jpg"
  },
  {
    "id": 9,
    "name": "LVB vs GBR",
    "imageSrc": "https://akthemes.com/video/images/matches/07.jpg"
  },
  {
    "id": 10,
    "name": "LVB vs GBR",
    "imageSrc": "https://akthemes.com/video/images/matches/07.jpg"
  },
  {
    "id": 11,
    "name": "LVB vs GBR",
    "imageSrc": "https://akthemes.com/video/images/matches/06.jpg"
  },
  {
    "id": 12,
    "name": "LVB vs GBR",
    "imageSrc": "https://akthemes.com/video/images/matches/07.jpg"
  },
  {
    "id": 13,
    "name": "LVB vs GBR",
    "imageSrc": "https://akthemes.com/video/images/matches/07.jpg"
  },
  {
    "id": 14,
    "name": "LVB vs GBR",
    "imageSrc": "https://akthemes.com/video/images/matches/07.jpg"
  },
  {
    "id": 15,
    "name": "LVB vs GBR",
    "imageSrc": "https://akthemes.com/video/images/matches/07.jpg"
  }
]